{
  "n": 32,
  "OS": "Linux",
  "BLAS": "mkl",
  "CPU": "Intel(R) Core(TM) i5-5200U CPU @ 2.20GHz",
  "WORD_SIZE": 64,
  "CPU_CORES": 4,
  "models": [
    {
      "formula": "Y ~ 1 + U * A + (1|G)",
      "fits": [
        {
          "optimizer": "bobyqa",
          "time": 0.576000000000001,
          "feval": 19,
          "func": "lmer",
          "dev": 9.97095587386469
        },
        {
          "optimizer": "Nelder_Mead",
          "time": 0.0209999999999972,
          "feval": 44,
          "func": "lmer",
          "dev": 9.97095587386805
        },
        {
          "optimizer": "nloptwrap",
          "time": 0.0479999999999983,
          "algorithm": "NLOPT_LN_BOBYQA",
          "feval": 10,
          "func": "lmer",
          "dev": 9.97095587386736
        },
        {
          "optimizer": "nloptwrap",
          "time": 0.0229999999999997,
          "algorithm": "NLOPT_LN_COBYLA",
          "feval": 24,
          "func": "lmer",
          "dev": 9.97095587393868
        },
        {
          "optimizer": "nloptwrap",
          "time": 5.006,
          "algorithm": "NLOPT_LN_PRAXIS",
          "feval": 100000,
          "func": "lmer",
          "dev": 9.97095587386467
        },
        {
          "optimizer": "nloptwrap",
          "time": 0.0210000000000008,
          "algorithm": "NLOPT_LN_NELDERMEAD",
          "feval": 24,
          "func": "lmer",
          "dev": 9.97095598038161
        },
        {
          "optimizer": "nloptwrap",
          "time": 0.022000000000002,
          "algorithm": "NLOPT_LN_SBPLX",
          "feval": 30,
          "func": "lmer",
          "dev": 9.9709559803816
        },
        {
          "optimizer": "optimx",
          "method": "L-BFGS-B",
          "time": 0.111000000000001,
          "feval": 14,
          "func": "lmer",
          "dev": 9.97095587386478
        },
        {
          "optimizer": "optimx",
          "method": "nlminb",
          "time": 0.128999999999998,
          "feval": 15,
          "func": "lmer",
          "dev": 9.97095587386587
        },
        {
          "optimizer": "optimx",
          "method": "spg",
          "time": 0.222000000000001,
          "feval": "NA",
          "func": "lmer",
          "dev": 9.97095587386474
        },
        {
          "optimizer": "optimx",
          "method": "bobyqa",
          "time": 0.109000000000002,
          "feval": "NA",
          "func": "lmer",
          "dev": 9.97095587386469
        },
        {
          "optimizer": "LN_BOBYQA",
          "time": 0.001230319,
          "geval": 0,
          "feval": 20,
          "func": "lmm",
          "dev": 9.970955873864689
        },
        {
          "optimizer": "LN_COBYLA",
          "time": 0.001433634,
          "geval": 0,
          "feval": 24,
          "func": "lmm",
          "dev": 9.970955874594186
        },
        {
          "optimizer": "LN_NELDERMEAD",
          "time": 0.001517056,
          "geval": 0,
          "feval": 30,
          "func": "lmm",
          "dev": 9.970955874852226
        },
        {
          "optimizer": "LN_SBPLX",
          "time": 0.002173187,
          "geval": 0,
          "feval": 45,
          "func": "lmm",
          "dev": 9.970955874852226
        },
        {
          "optimizer": "LD_MMA",
          "time": 0.00112071,
          "geval": 12,
          "feval": 12,
          "func": "lmm",
          "dev": 9.970955873884336
        },
        {
          "optimizer": "LD_CCSAQ",
          "time": 0.001019733,
          "geval": 11,
          "feval": 11,
          "func": "lmm",
          "dev": 9.970955873866355
        },
        {
          "optimizer": "LD_SLSQP",
          "time": 0.001090676,
          "geval": 10,
          "feval": 13,
          "func": "lmm",
          "dev": 9.970955873864675
        },
        {
          "optimizer": "LD_LBFGS",
          "time": 0.00335816,
          "geval": 15,
          "feval": 15,
          "func": "lmm",
          "dev": 9.970955873864671
        },
        {
          "optimizer": "LD_TNEWTON",
          "time": 0.003703762,
          "geval": 13,
          "feval": 13,
          "func": "lmm",
          "dev": 9.970955873864693
        },
        {
          "optimizer": "LD_TNEWTON_PRECOND",
          "time": 0.003331102,
          "geval": 13,
          "feval": 13,
          "func": "lmm",
          "dev": 9.970955873864693
        },
        {
          "optimizer": "LD_TNEWTON_RESTART",
          "time": 0.003082527,
          "geval": 19,
          "feval": 19,
          "func": "lmm",
          "dev": 9.970955873864682
        },
        {
          "optimizer": "LD_TNEWTON_PRECOND_RESTART",
          "time": 0.003547291,
          "geval": 19,
          "feval": 19,
          "func": "lmm",
          "dev": 9.970955873864675
        },
        {
          "optimizer": "LD_VAR1",
          "time": 0.001981427,
          "geval": 12,
          "feval": 12,
          "func": "lmm",
          "dev": 9.970955873864678
        },
        {
          "optimizer": "LD_VAR2",
          "time": 0.001993129,
          "geval": 12,
          "feval": 12,
          "func": "lmm",
          "dev": 9.970955873864678
        }
      ],
      "q": [
        8
      ],
      "nopt": 1,
      "p": 8,
      "mtype": "PLSOne"
    },
    {
      "formula": "Y ~ 1 + U + A + (1|G)",
      "fits": [
        {
          "optimizer": "bobyqa",
          "time": 0.0159999999999982,
          "feval": 17,
          "func": "lmer",
          "dev": 13.6172156265855
        },
        {
          "optimizer": "Nelder_Mead",
          "time": 0.0199999999999996,
          "feval": 40,
          "func": "lmer",
          "dev": 13.6172156265947
        },
        {
          "optimizer": "nloptwrap",
          "time": 0.0209999999999972,
          "algorithm": "NLOPT_LN_BOBYQA",
          "feval": 15,
          "func": "lmer",
          "dev": 13.6172156265855
        },
        {
          "optimizer": "nloptwrap",
          "time": 0.0199999999999996,
          "algorithm": "NLOPT_LN_COBYLA",
          "feval": 21,
          "func": "lmer",
          "dev": 13.6172156273147
        },
        {
          "optimizer": "nloptwrap",
          "time": 4.743,
          "algorithm": "NLOPT_LN_PRAXIS",
          "feval": 100000,
          "func": "lmer",
          "dev": 13.6172156265855
        },
        {
          "optimizer": "nloptwrap",
          "time": 0.0209999999999972,
          "algorithm": "NLOPT_LN_NELDERMEAD",
          "feval": 22,
          "func": "lmer",
          "dev": 13.6172164453925
        },
        {
          "optimizer": "nloptwrap",
          "time": 0.0210000000000008,
          "algorithm": "NLOPT_LN_SBPLX",
          "feval": 30,
          "func": "lmer",
          "dev": 13.6172156273147
        },
        {
          "optimizer": "optimx",
          "method": "L-BFGS-B",
          "time": 0.111000000000001,
          "feval": 16,
          "func": "lmer",
          "dev": 13.6172156265856
        },
        {
          "optimizer": "optimx",
          "method": "nlminb",
          "time": 0.108999999999998,
          "feval": 17,
          "func": "lmer",
          "dev": 13.617215626587
        },
        {
          "optimizer": "optimx",
          "method": "spg",
          "time": 0.199999999999999,
          "feval": "NA",
          "func": "lmer",
          "dev": 13.6172156265855
        },
        {
          "optimizer": "optimx",
          "method": "bobyqa",
          "time": 0.108000000000001,
          "feval": "NA",
          "func": "lmer",
          "dev": 13.6172156265855
        },
        {
          "optimizer": "LN_BOBYQA",
          "time": 0.001091359,
          "geval": 0,
          "feval": 17,
          "func": "lmm",
          "dev": 13.617215626585473
        },
        {
          "optimizer": "LN_COBYLA",
          "time": 0.001346021,
          "geval": 0,
          "feval": 23,
          "func": "lmm",
          "dev": 13.61721563485207
        },
        {
          "optimizer": "LN_NELDERMEAD",
          "time": 0.001670247,
          "geval": 0,
          "feval": 32,
          "func": "lmm",
          "dev": 13.61721562836805
        },
        {
          "optimizer": "LN_SBPLX",
          "time": 0.002374103,
          "geval": 0,
          "feval": 52,
          "func": "lmm",
          "dev": 13.617215626665303
        },
        {
          "optimizer": "LD_MMA",
          "time": 0.001183903,
          "geval": 14,
          "feval": 14,
          "func": "lmm",
          "dev": 13.617215626585594
        },
        {
          "optimizer": "LD_CCSAQ",
          "time": 0.001052268,
          "geval": 11,
          "feval": 11,
          "func": "lmm",
          "dev": 13.617215626600604
        },
        {
          "optimizer": "LD_SLSQP",
          "time": 0.001060384,
          "geval": 10,
          "feval": 13,
          "func": "lmm",
          "dev": 13.617215626585487
        },
        {
          "optimizer": "LD_LBFGS",
          "time": 0.003164759,
          "geval": 11,
          "feval": 11,
          "func": "lmm",
          "dev": 13.617215626585455
        },
        {
          "optimizer": "LD_TNEWTON",
          "time": 0.002802386,
          "geval": 13,
          "feval": 13,
          "func": "lmm",
          "dev": 13.617215626585473
        },
        {
          "optimizer": "LD_TNEWTON_PRECOND",
          "time": 0.003225364,
          "geval": 13,
          "feval": 13,
          "func": "lmm",
          "dev": 13.61721562658547
        },
        {
          "optimizer": "LD_TNEWTON_RESTART",
          "time": 0.002884671,
          "geval": 14,
          "feval": 14,
          "func": "lmm",
          "dev": 13.617215626585462
        },
        {
          "optimizer": "LD_TNEWTON_PRECOND_RESTART",
          "time": 0.003261046,
          "geval": 14,
          "feval": 14,
          "func": "lmm",
          "dev": 13.617215626585477
        },
        {
          "optimizer": "LD_VAR1",
          "time": 0.002007813,
          "geval": 11,
          "feval": 11,
          "func": "lmm",
          "dev": 13.617215626585455
        },
        {
          "optimizer": "LD_VAR2",
          "time": 0.001919391,
          "geval": 11,
          "feval": 11,
          "func": "lmm",
          "dev": 13.617215626585455
        }
      ],
      "q": [
        8
      ],
      "nopt": 1,
      "p": 5,
      "mtype": "PLSOne"
    }
  ],
  "Julia": "0.3.10-pre+4",
  "memory": "5.745 GB",
  "dsname": "AvgDailyGain"
}
