{
  "BLAS": "openblas",
  "CPU": "Intel(R) Core(TM) i5-3570 CPU @ 3.40GHz",
  "models": [
    {
      "formula": "Y ~ 1 + U + ((1 + U) | G)",
      "fits": [
        {
          "optimizer": "bobyqa",
          "time": 0.0660000000002583,
          "feval": 874,
          "func": "lmer",
          "dev": 182.055576388265
        },
        {
          "optimizer": "Nelder_Mead",
          "time": 0.0390000000002146,
          "feval": 232,
          "func": "lmer",
          "dev": 182.055576388145
        },
        {
          "optimizer": "NLOPT_LN_BOBYQA",
          "time": 0.0270000000000437,
          "feval": 121,
          "func": "lmer",
          "dev": 182.055576620308
        },
        {
          "optimizer": "NLOPT_LN_COBYLA",
          "time": 1.34799999999996,
          "feval": 24837,
          "func": "lmer",
          "dev": 182.257777237231
        },
        {
          "optimizer": "NLOPT_LN_NELDERMEAD",
          "time": 0.0300000000002001,
          "feval": 188,
          "func": "lmer",
          "dev": 182.055576929728
        },
        {
          "optimizer": "NLOPT_LN_SBPLX",
          "time": 0.0380000000000109,
          "feval": 334,
          "func": "lmer",
          "dev": 182.055576472896
        },
        {
          "optimizer": "optimx:L-BFGS-B",
          "time": 0.135999999999967,
          "feval": 60,
          "func": "lmer",
          "dev": 182.055576515493
        },
        {
          "optimizer": "optimx:nlminb",
          "time": 0.130000000000109,
          "feval": 123,
          "func": "lmer",
          "dev": 182.055576388148
        },
        {
          "optimizer": "optimx:spg",
          "time": 0.672000000000025,
          "feval": "NA",
          "func": "lmer",
          "dev": 182.057407417186
        },
        {
          "optimizer": "optimx:bobyqa",
          "time": 0.170000000000073,
          "feval": "NA",
          "func": "lmer",
          "dev": 182.055576388265
        },
        {
          "optimizer": "LN_BOBYQA",
          "time": 0.004841648,

          "feval": 139,
          "func": "lmm",
          "dev": 182.05557644315462
        },
        {
          "optimizer": "LN_COBYLA",
          "time": 3.483907318,

          "feval": 97712,
          "func": "lmm",
          "dev": 182.0555944198405
        },
        {
          "optimizer": "LN_PRAXIS",
          "time": 0.006534394,

          "feval": 210,
          "func": "lmm",
          "dev": 182.055576395053
        },
        {
          "optimizer": "LN_NELDERMEAD",
          "time": 0.006431806,

          "feval": 213,
          "func": "lmm",
          "dev": 182.05557639258012
        },
        {
          "optimizer": "LN_SBPLX",
          "time": 0.011045452,

          "feval": 386,
          "func": "lmm",
          "dev": 182.05557639308353
        }
      ],
      "q": [
        20
      ],
      "nopt": 3,
      "p": 2
    }
  ],
  "memory": "15.561 GB",
  "CPU_CORES": 4,
  "WORD_SIZE": 64,
  "Julia": "0.4.2",
  "Rversion": "R version 3.2.2 (2015-08-14)",
  "dsname": "WWheat",
  "OS": "Linux",
  "n": 60
}
